setup.py
elsa_client.egg-info/PKG-INFO
elsa_client.egg-info/SOURCES.txt
elsa_client.egg-info/dependency_links.txt
elsa_client.egg-info/requires.txt
elsa_client.egg-info/top_level.txt
reg/__init__.py
reg/registerer.py
tests/__init__.py
tests/registerer_test.py