Metadata-Version: 1.1
Name: elsa-client
Version: 0.1.0
Summary: Service registration client for Cytoscape CI ELSA
Home-page: https://github.com/idekerlab/py2cytoscape
Author: Keiichiro Ono
Author-email: kono@ucsd.edu
License: MIT License
Keywords: cytoscape,bioinformatics,graph,network,microservice
Platform: UNKNOWN
Classifier: Intended Audience :: Science/Research
Classifier: Intended Audience :: Developers
Classifier: Operating System :: OS Independent
Classifier: Development Status :: 3 - Alpha
Classifier: Programming Language :: Python :: 2.7
Classifier: Programming Language :: Python :: 3.4
Classifier: Programming Language :: Python :: 3.5
Classifier: License :: OSI Approved :: MIT License
Classifier: Topic :: Scientific/Engineering :: Bio-Informatics
Classifier: Topic :: Scientific/Engineering :: Information Analysis
Classifier: Topic :: Scientific/Engineering :: Mathematics
